odoo8_addon_account_voucher_supplier_invoice_number-8.0.1.0.0.99.dev9-py2.7-nspkg.pth
odoo8_addon_account_voucher_supplier_invoice_number-8.0.1.0.0.99.dev9.dist-info/METADATA
odoo8_addon_account_voucher_supplier_invoice_number-8.0.1.0.0.99.dev9.dist-info/RECORD
odoo8_addon_account_voucher_supplier_invoice_number-8.0.1.0.0.99.dev9.dist-info/WHEEL
odoo8_addon_account_voucher_supplier_invoice_number-8.0.1.0.0.99.dev9.dist-info/namespace_packages.txt
odoo8_addon_account_voucher_supplier_invoice_number-8.0.1.0.0.99.dev9.dist-info/top_level.txt
odoo_addons/account_voucher_supplier_invoice_number/README.rst
odoo_addons/account_voucher_supplier_invoice_number/__init__.py
odoo_addons/account_voucher_supplier_invoice_number/__openerp__.py
odoo_addons/account_voucher_supplier_invoice_number/i18n/account_voucher_supplier_invoice_number.pot
odoo_addons/account_voucher_supplier_invoice_number/i18n/de.po
odoo_addons/account_voucher_supplier_invoice_number/i18n/es.po
odoo_addons/account_voucher_supplier_invoice_number/i18n/fr.po
odoo_addons/account_voucher_supplier_invoice_number/i18n/sl.po
odoo_addons/account_voucher_supplier_invoice_number/models/__init__.py
odoo_addons/account_voucher_supplier_invoice_number/models/account_voucher.py
odoo_addons/account_voucher_supplier_invoice_number/models/account_voucher_line.py
odoo_addons/account_voucher_supplier_invoice_number/static/description/icon.png
odoo_addons/account_voucher_supplier_invoice_number/tests/__init__.py
odoo_addons/account_voucher_supplier_invoice_number/tests/test_account_voucher.py
odoo_addons/account_voucher_supplier_invoice_number/views/account_voucher.xml
